{"cameraMode":{"drawMode":0,"name":"Shaded","section":"Shading Mode"},"sceneLighting":true,"audioPlay":false,"sceneViewState":{"m_AlwaysRefresh":false,"showFog":true,"showSkybox":true,"showFlares":true,"showImageEffects":true,"showParticleSystems":true,"showVisualEffectGraphs":true,"m_FxEnabled":true},"in2DMode":false,"pivot":{"x":11.236174583435059,"y":-5.19384241104126,"z":-35.615447998046878},"rotation":{"x":0.1028749942779541,"y":0.8411058783531189,"z":-0.17214669287204743,"w":0.5024421215057373},"size":10.0,"orthographic":false}